Workbook

Sheet IBOR - Book of Records
A1: INVESTMENT BOOK OF RECORDS (IBOR) — As at 30 June 2026
A2: Fund: Rathbones Multi-Asset Growth Fund | Fund Manager: J. Smith | Custodian: BNY Mellon | Market Data: Bloomberg
A4: Security ID (ISIN) | B4: Security Name | C4: Asset Class | D4: CCY | E4: Quantity (Units) | F4: Avg Cost Price | G4: Cost Basis (GBP) | H4: Market Price (Close) | I4: Price Source | J4: Market Value (GBP) | K4: Unrealised P&L (GBP) | L4: Weight (%) | M4: Custodian Qty | N4: Qty Variance | O4: Custodian Mkt Value | P4: Value Variance
A5: GB00B3FFY088 | B5: Shell PLC | C5: UK Equity | D5: GBP | E5: 150000 | F5: 24.35 | G5: =E5*F5 -> 3652500 | H5: 26.82 | I5: Bloomberg | J5: =E5*H5 -> 4023000 | K5: =J5-G5 -> 370500 | L5: =J5/J$13 -> 0.0076689814 | M5: 150000 | N5: =E5-M5 -> 0 | O5: =M5*H5 -> 4023000 | P5: =J5-O5 -> 0
A6: GB0007188757 | B6: Rio Tinto PLC | C6: UK Equity | D6: GBP | E6: 85000 | F6: 52.1 | G6: =E6*F6 -> 4428500 | H6: 54.75 | I6: Bloomberg | J6: =E6*H6 -> 4653750 | K6: =J6-G6 -> 225250 | L6: =J6/J$13 -> 0.0088713701 | M6: 85000 | N6: =E6-M6 -> 0 | O6: =M6*H6 -> 4653750 | P6: =J6-O6 -> 0
A7: US0378331005 | B7: Apple Inc | C7: US Equity | D7: USD | E7: 40000 | F7: 178.5 | G7: =E7*F7 -> 7140000 | H7: 195.2 | I7: Bloomberg | J7: =E7*H7 -> 7808000 | K7: =J7-G7 -> 668000 | L7: =J7/J$13 -> 0.014884267 | M7: 40000 | N7: =E7-M7 -> 0 | O7: =M7*H7 -> 7808000 | P7: =J7-O7 -> 0
A8: DE0007164600 | B8: SAP SE | C8: EU Equity | D8: EUR | E8: 25000 | F8: 165 | G8: =E8*F8 -> 4125000 | H8: 182.4 | I8: Bloomberg | J8: =E8*H8 -> 4560000 | K8: =J8-G8 -> 435000 | L8: =J8/J$13 -> 0.008692656 | M8: 25000 | N8: =E8-M8 -> 0 | O8: =M8*H8 -> 4560000 | P8: =J8-O8 -> 0
A9: GB00B24CGK77 | B9: Reckitt Benckiser | C9: UK Equity | D9: GBP | E9: 60000 | F9: 58.9 | G9: =E9*F9 -> 3534000 | H9: 55.2 | I9: Bloomberg | J9: =E9*H9 -> 3312000 | K9: =J9-G9 -> -222000 | L9: =J9/J$13 -> 0.0063136133 | M9: 60000 | N9: =E9-M9 -> 0 | O9: =M9*H9 -> 3312000 | P9: =J9-O9 -> 0
A10: XS2530200896 | B10: UK Gilt 3.5% 2028 | C10: Fixed Income | D10: GBP | E10: 5000000 | F10: 98.5 | G10: =E10*F10 -> 492500000 | H10: 99.15 | I10: Bloomberg | J10: =E10*H10 -> 495750000 | K10: =J10-G10 -> 3250000 | L10: =J10/J$13 -> 0.9450404 | M10: 5000000 | N10: =E10-M10 -> 0 | O10: =M10*H10 -> 495750000 | P10: =J10-O10 -> 0
A11: GB00BHJYC057 | B11: iShares Core FTSE 100 | C11: ETF | D11: GBP | E11: 200000 | F11: 7.85 | G11: =E11*F11 -> 1570000 | H11: 8.12 | I11: Bloomberg | J11: =E11*H11 -> 1624000 | K11: =J11-G11 -> 54000 | L11: =J11/J$13 -> 0.0030958056 | M11: 200000 | N11: =E11-M11 -> 0 | O11: =M11*H11 -> 1624000 | P11: =J11-O11 -> 0
A12: CASH_GBP | B12: GBP Cash Balance | C12: Cash | D12: GBP | E12: 2850000 | F12: 1 | G12: =E12*F12 -> 2850000 | H12: 1 | I12: Internal | J12: =E12*H12 -> 2850000 | K12: =J12-G12 -> 0 | L12: =J12/J$13 -> 0.00543291 | M12: 2850000 | N12: =E12-M12 -> 0 | O12: =M12*H12 -> 2850000 | P12: =J12-O12 -> 0
A13: TOTAL | G13: =SUM(G5:G12) -> 519800000 | J13: =SUM(J5:J12) -> 524580750 | K13: =SUM(K5:K12) -> 4780750 | L13: =SUM(L5:L12) -> 1 | O13: =SUM(O5:O12) -> 524580750 | P13: =SUM(P5:P12) -> 0

Sheet Custodian Reconciliation
A1: CUSTODIAN STATEMENT RECONCILIATION — BNY Mellon vs IBOR — 30 June 2026
A2: Reconciliation Frequency: Daily (T+1) | Tolerance: Quantity = 0 units; Value = ±£500 | Regulation: FCA CASS 6.6, SYSC 9.1
A4: ISIN | B4: Security Name | C4: IBOR Quantity | D4: Custodian Quantity | E4: Qty Difference | F4: IBOR Market Value (GBP) | G4: Custodian Market Value (GBP) | H4: Value Difference (GBP) | I4: Status | J4: Break Reason | K4: Action Required | L4: Resolution Date
A5: GB00B3FFY088 | B5: Shell PLC | C5: 150000 | D5: 150000 | E5: =C5-D5 -> 0 | F5: ='IBOR - Book of Records'!J5 -> 4023000 | G5: =D5*'IBOR - Book of Records'!H5 -> 4023000 | H5: =F5-G5 -> 0 | I5: =IF(AND(E5=0,ABS(H5)<=500),"MATCHED","BREAK") -> MATCHED
A6: GB0007188757 | B6: Rio Tinto PLC | C6: 85000 | D6: 85000 | E6: =C6-D6 -> 0 | F6: ='IBOR - Book of Records'!J6 -> 4653750 | G6: =D6*'IBOR - Book of Records'!H6 -> 4653750 | H6: =F6-G6 -> 0 | I6: =IF(AND(E6=0,ABS(H6)<=500),"MATCHED","BREAK") -> MATCHED
A7: US0378331005 | B7: Apple Inc | C7: 40000 | D7: 40000 | E7: =C7-D7 -> 0 | F7: ='IBOR - Book of Records'!J7 -> 7808000 | G7: =D7*'IBOR - Book of Records'!H7 -> 7808000 | H7: =F7-G7 -> 0 | I7: =IF(AND(E7=0,ABS(H7)<=500),"MATCHED","BREAK") -> MATCHED
A8: DE0007164600 | B8: SAP SE | C8: 25000 | D8: 25000 | E8: =C8-D8 -> 0 | F8: ='IBOR - Book of Records'!J8 -> 4560000 | G8: =D8*'IBOR - Book of Records'!H8 -> 4560000 | H8: =F8-G8 -> 0 | I8: =IF(AND(E8=0,ABS(H8)<=500),"MATCHED","BREAK") -> MATCHED
A9: GB00B24CGK77 | B9: Reckitt Benckiser | C9: 60000 | D9: 59500 | E9: =C9-D9 -> 500 | F9: ='IBOR - Book of Records'!J9 -> 3312000 | G9: =D9*'IBOR - Book of Records'!H9 -> 3284400 | H9: =F9-G9 -> 27600 | I9: =IF(AND(E9=0,ABS(H9)<=500),"MATCHED","BREAK") -> BREAK | J9: Corp action pending | K9: Investigate bonus shares
A10: XS2530200896 | B10: UK Gilt 3.5% 2028 | C10: 5000000 | D10: 5000000 | E10: =C10-D10 -> 0 | F10: ='IBOR - Book of Records'!J10 -> 495750000 | G10: =D10*'IBOR - Book of Records'!H10 -> 495750000 | H10: =F10-G10 -> 0 | I10: =IF(AND(E10=0,ABS(H10)<=500),"MATCHED","BREAK") -> MATCHED
A11: GB00BHJYC057 | B11: iShares Core FTSE 100 | C11: 200000 | D11: 200000 | E11: =C11-D11 -> 0 | F11: ='IBOR - Book of Records'!J11 -> 1624000 | G11: =D11*'IBOR - Book of Records'!H11 -> 1624000 | H11: =F11-G11 -> 0 | I11: =IF(AND(E11=0,ABS(H11)<=500),"MATCHED","BREAK") -> MATCHED
A12: CASH_GBP | B12: GBP Cash Balance | C12: 2850000 | D12: 2847500 | E12: =C12-D12 -> 2500 | F12: ='IBOR - Book of Records'!J12 -> 2850000 | G12: =D12*'IBOR - Book of Records'!H12 -> 2847500 | H12: =F12-G12 -> 2500 | I12: =IF(AND(E12=0,ABS(H12)<=500),"MATCHED","BREAK") -> BREAK | J12: Unsettled trade T+2 | K12: Confirm settlement
A14: RECONCILIATION SUMMARY
A15: Total Positions: | B15: =COUNTA(A5:A12) -> 8
A16: Matched: | B16: =COUNTIF(I5:I12,"MATCHED") -> 6
A17: Breaks: | B17: =COUNTIF(I5:I12,"BREAK") -> 2
A18: Match Rate: | B18: =B16/B15 -> 0.75

Sheet Market Data Reconciliation
A1: MARKET DATA VENDOR PRICE RECONCILIATION — 30 June 2026
A2: Primary: Bloomberg | Secondary: Refinitiv | Tolerance: ±0.5% | Regulation: FCA FUND 3.9, COBS 11.5A
A4: ISIN | B4: Security Name | C4: CCY | D4: Bloomberg Close Price | E4: Refinitiv Close Price | F4: Custodian Price | G4: Bloom vs Refin Diff | H4: Bloom vs Refin % | I4: Bloom vs Custodian Diff | J4: Bloom vs Custodian % | K4: Status | L4: Price Used in IBOR | M4: Override Reason | N4: Approved By
A5: GB00B3FFY088 | B5: Shell PLC | C5: GBP | D5: 26.82 | E5: 26.8 | F5: 26.82 | G5: =D5-E5 -> 0.02 | H5: =IF(E5=0,0,ABS(G5/E5)) -> 0.00074626866 | I5: =D5-F5 -> 0 | J5: =IF(F5=0,0,ABS(I5/F5)) -> 0 | K5: =IF(AND(H5<=0.005,J5<=0.005),"MATCHED","REVIEW") -> MATCHED | L5: =D5 -> 26.82
A6: GB0007188757 | B6: Rio Tinto PLC | C6: GBP | D6: 54.75 | E6: 54.78 | F6: 54.75 | G6: =D6-E6 -> -0.03 | H6: =IF(E6=0,0,ABS(G6/E6)) -> 0.00054764513 | I6: =D6-F6 -> 0 | J6: =IF(F6=0,0,ABS(I6/F6)) -> 0 | K6: =IF(AND(H6<=0.005,J6<=0.005),"MATCHED","REVIEW") -> MATCHED | L6: =D6 -> 54.75
A7: US0378331005 | B7: Apple Inc | C7: USD | D7: 195.2 | E7: 195.15 | F7: 195.2 | G7: =D7-E7 -> 0.05 | H7: =IF(E7=0,0,ABS(G7/E7)) -> 0.00025621317 | I7: =D7-F7 -> 0 | J7: =IF(F7=0,0,ABS(I7/F7)) -> 0 | K7: =IF(AND(H7<=0.005,J7<=0.005),"MATCHED","REVIEW") -> MATCHED | L7: =D7 -> 195.2
A8: DE0007164600 | B8: SAP SE | C8: EUR | D8: 182.4 | E8: 182.55 | F8: 182.4 | G8: =D8-E8 -> -0.15 | H8: =IF(E8=0,0,ABS(G8/E8)) -> 0.00082169269 | I8: =D8-F8 -> 0 | J8: =IF(F8=0,0,ABS(I8/F8)) -> 0 | K8: =IF(AND(H8<=0.005,J8<=0.005),"MATCHED","REVIEW") -> MATCHED | L8: =D8 -> 182.4
A9: GB00B24CGK77 | B9: Reckitt Benckiser | C9: GBP | D9: 55.2 | E9: 55.18 | F9: 55.2 | G9: =D9-E9 -> 0.02 | H9: =IF(E9=0,0,ABS(G9/E9)) -> 0.00036245016 | I9: =D9-F9 -> 0 | J9: =IF(F9=0,0,ABS(I9/F9)) -> 0 | K9: =IF(AND(H9<=0.005,J9<=0.005),"MATCHED","REVIEW") -> MATCHED | L9: =D9 -> 55.2
A10: XS2530200896 | B10: UK Gilt 3.5% 2028 | C10: GBP | D10: 99.15 | E10: 99.12 | F10: 99.1 | G10: =D10-E10 -> 0.03 | H10: =IF(E10=0,0,ABS(G10/E10)) -> 0.00030266344 | I10: =D10-F10 -> 0.05 | J10: =IF(F10=0,0,ABS(I10/F10)) -> 0.00050454087 | K10: =IF(AND(H10<=0.005,J10<=0.005),"MATCHED","REVIEW") -> MATCHED | L10: =D10 -> 99.15
A11: GB00BHJYC057 | B11: iShares Core FTSE 100 | C11: GBP | D11: 8.12 | E11: 8.11 | F11: 8.12 | G11: =D11-E11 -> 0.01 | H11: =IF(E11=0,0,ABS(G11/E11)) -> 0.0012330456 | I11: =D11-F11 -> 0 | J11: =IF(F11=0,0,ABS(I11/F11)) -> 0 | K11: =IF(AND(H11<=0.005,J11<=0.005),"MATCHED","REVIEW") -> MATCHED | L11: =D11 -> 8.12
A13: STALE PRICE CHECK
A14: ISIN | B14: Security Name | C14: Today Price | D14: Prior Day Price | E14: Day Change % | F14: Days Unchanged | G14: Status
A15: GB00B3FFY088 | B15: Shell PLC | C15: 26.82 | D15: 26.5 | E15: =IF(D15=0,0,(C15-D15)/D15) -> 0.012075472 | F15: 0 | G15: OK
A16: XS2530200896 | B16: UK Gilt 3.5% 2028 | C16: 99.15 | D16: 99.15 | E16: =IF(D16=0,0,(C16-D16)/D16) -> 0 | F16: 3 | G16: REVIEW

Sheet Corporate Actions
A1: CORPORATE ACTIONS PROCESSING & RECONCILIATION LOG — Q2 2026
A2: Source: Bloomberg CACT / BNY Mellon Custodian Notifications | Regulation: COBS 11.3, COBS 11.5A, CASS 6
A4: Event ID | B4: ISIN | C4: Security Name | D4: Event Type | E4: Announce Date | F4: Ex-Date | G4: Record Date | H4: Pay Date | I4: Rate / Terms | J4: Qty Held (Ex-Date) | K4: Entitlement (IBOR Calc) | L4: Custodian Entitlement | M4: Entitlement Variance | N4: Amount Received (GBP) | O4: Status | P4: Notes
A5: CA-2026-001 | B5: GB00B3FFY088 | C5: Shell PLC | D5: Cash Dividend | E5: 01/05/2026 | F5: 15/05/2026 | G5: 16/05/2026 | H5: 28/06/2026 | I5: GBP 0.287 per share | J5: 150000 | K5: =J5*0.287 -> 43050 | L5: 43050 | M5: =K5-L5 -> 0 | N5: 43050 | O5: Settled | P5: Q1 2026 interim dividend
A6: CA-2026-002 | B6: GB0007188757 | C6: Rio Tinto PLC | D6: Cash Dividend | E6: 22/04/2026 | F6: 08/05/2026 | G6: 09/05/2026 | H6: 19/06/2026 | I6: USD 2.25 per share | J6: 85000 | K6: =J6*2.25 -> 191250 | L6: 191250 | M6: =K6-L6 -> 0 | N6: 150380 | O6: Settled | P6: Final dividend FY2025
A7: CA-2026-003 | B7: GB00B24CGK77 | C7: Reckitt Benckiser | D7: Bonus Issue | E7: 10/06/2026 | F7: 25/06/2026 | G7: 26/06/2026 | H7: 30/06/2026 | I7: 1 new for 120 held | J7: 60000 | K7: =J7/120 -> 500 | L7: 500 | M7: =K7-L7 -> 0 | O7: Pending | P7: Awaiting custodian confirmation
A8: CA-2026-004 | B8: US0378331005 | C8: Apple Inc | D8: Stock Split | E8: 01/04/2026 | F8: 15/04/2026 | G8: 14/04/2026 | H8: 15/04/2026 | I8: 4:1 split | J8: 10000 | K8: =J8*4 -> 40000 | L8: 40000 | M8: =K8-L8 -> 0 | N8: N/A | O8: Settled | P8: Pre-split qty 10,000; post-split 40,000
A9: CA-2026-005 | B9: XS2530200896 | C9: UK Gilt 3.5% 2028 | D9: Coupon Payment | E9: 01/01/2026 | F9: 22/06/2026 | G9: 22/06/2026 | H9: 22/06/2026 | I9: 3.5% semi-annual | J9: 5000000 | K9: =J9*0.035/2 -> 87500 | L9: 87500 | M9: =K9-L9 -> 0 | N9: 87500 | O9: Settled | P9: Semi-annual coupon
A10: CA-2026-006 | B10: DE0007164600 | C10: SAP SE | D10: Rights Issue | E10: 20/05/2026 | F10: 05/06/2026 | G10: 06/06/2026 | H10: 20/06/2026 | I10: 1 right per 10 shares at EUR 150 | J10: 25000 | K10: =J10/10 -> 2500 | L10: 2500 | M10: =K10-L10 -> 0 | N10: 2500 | O10: Elected | P10: Elected to take up full entitlement
A12: CORPORATE ACTION PROCESSING CHECKLIST
A13: Step | B13: Description | C13: Responsible | D13: Completed | E13: Date | F13: Regulatory Basis
A14: 1 | B14: Event notification received from custodian / Bloomberg | C14: Operations | D14: Yes | E14: Same day | F14: COBS 11.3
A15: 2 | B15: Event details verified against multiple sources | C15: Operations | D15: Yes | E15: T+1 | F15: SYSC 9.1
A16: 3 | B16: Entitlement calculated and cross-checked | C16: Middle Office | D16: Yes | E16: T+1 | F16: CASS 6.6
A17: 4 | B17: Election decision recorded (if voluntary) | C17: Portfolio Mgr | D17: Yes | E17: Before deadline | F17: COBS 11.5A
A18: 5 | B18: Custodian entitlement matched to IBOR calculation | C18: Operations | D18: Yes | E18: Pay date | F18: CASS 6.6
A19: 6 | B19: Cash / securities received and booked | C19: Operations | D19: Yes | E19: Pay date | F19: CASS 6.2, CASS 7
A20: 7 | B20: NAV impact assessed and fund accounts updated | C20: Fund Accounting | D20: Yes | E20: Pay date | F20: FUND 3.9
A21: 8 | B21: Breaks investigated and escalated if unresolved >3 days | C21: Compliance | D21: Ongoing | F21: SYSC 9.1, COBS 2.1

Sheet Regulatory Reference
A1: FCA REGULATORY FRAMEWORK — RECORD KEEPING FOR ASSET MANAGEMENT FIRMS
A3: Regulation / Rule | B3: Sourcebook | C3: Record Type | D3: Minimum Retention | E3: Relevance to Reconciliation
A4: SYSC 9.1.1R | B4: SYSC | C4: General business records, internal organisation, all services & transactions | D4: 5 years (MiFID); as long as relevant (non-MiFID) | E4: Foundation rule: all IBOR records, trade blotters, position records
A5: SYSC 9.1.2R | B5: SYSC | C5: All records in relation to MiFID business | D5: At least 5 years | E5: Custodian recon records, order records, transaction records
A6: SYSC 10A | B6: SYSC | C6: Telephone conversations and electronic communications relating to transactions | D6: 5 years (up to 7 on FCA request) | E6: Recorded trade instructions, order confirmations, client calls
A7: COBS 9.5.2R | B7: COBS | C7: Suitability assessment records | D7: 5 years (life/pension products); Indefinite (pension transfers) | E7: Suitability of investment decisions documented and retained
A8: COBS 10.7 / 10A.7 | B8: COBS | C8: Appropriateness assessment records | D8: At least 5 years | E8: Records of appropriateness checks for execution-only services
A9: COBS 11.3 | B9: COBS | C9: Client order handling — prompt and accurate recording and allocation | D9: Duration of MiFID retention (5 yrs) | E9: Order allocation records, sequential execution evidence
A10: COBS 11.5A | B10: COBS | C10: Client orders and transactions — detailed record immediately on receipt | D10: 5 years | E10: Order details, trader ID, algorithm ID, timestamps, decision to deal
A11: COBS 4.11 | B11: COBS | C11: Financial promotions and approvals | D11: 5 years | E11: Marketing material records and approval evidence
A12: CASS 6.2 | B12: CASS | C12: Client asset custody — organisational arrangements, segregation records | D12: Duration of custody relationship | E12: Custodian reconciliation records, asset segregation evidence
A13: CASS 6.6 | B13: CASS | C13: Internal and external reconciliation of custody assets | D13: Monthly (minimum); daily if CSD | E13: Core custodian vs IBOR reconciliation; break logs and resolution
A14: CASS 7.15 | B14: CASS | C14: Client money reconciliation | D14: Daily internal reconciliation | E14: Cash balance reconciliation between IBOR and custodian
... A21: MAR (UK) | B21: Legislation | C21: Market Abuse Regulation — suspicious transaction reports | D21: 5 years | E21: STORs and supporting trade records for surveillance

Sheet Recon Controls Framework
A1: RECONCILIATION CONTROLS & GOVERNANCE FRAMEWORK
A3: Control ID | B3: Control Description | C3: Frequency | D3: Owner | E3: Regulatory Basis | F3: Evidence Required
A4: RC-001 | B4: Custodian holdings reconciliation (positions vs IBOR) | C4: Daily (T+1) | D4: Operations Manager | E4: CASS 6.6 SYSC 9.1 | F4: Recon report with break log, signed off by line manager
A5: RC-002 | B5: Cash balance reconciliation (custodian vs IBOR vs bank) | C5: Daily | D5: Treasury / Operations | E5: CASS 7.15 SYSC 9.1 | F5: Three-way cash recon report, break investigation log
A6: RC-003 | B6: Market data price verification (primary vs secondary vendor) | C6: Daily (close) | D6: Middle Office | E6: FUND 3.9 COBS 11.5A | F6: Price tolerance report, override approvals log
A7: RC-004 | B7: Stale / illiquid price review | C7: Daily | D7: Pricing Committee | E7: FUND 3.9 | F7: Stale price exception report, valuation committee minutes
A8: RC-005 | B8: Corporate action entitlement reconciliation (IBOR vs custodian) | C8: Per event (on pay date) | D8: Operations | E8: CASS 6.6 COBS 11.3 | F8: Entitlement calc sheet, custodian confirmation match
A9: RC-006 | B9: NAV calculation and verification | C9: Daily | D9: Fund Accounting | E9: FUND 3.9 COLL 6.3 | F9: NAV pack with price sources, shadow NAV comparison
A10: RC-007 | B10: Trade reconciliation (OMS vs execution venue vs custodian) | C10: Daily (T+1) | D10: Operations | E10: COBS 11.5A SYSC 9.1 | F10: Trade matching report, unmatched trade escalation log
A11: RC-008 | B11: Income reconciliation (expected vs received dividends/coupons) | C11: Per event + monthly review | D11: Fund Accounting | E11: CASS 6.6 CASS 7 | F11: Income accrual vs receipt report, withholding tax reconciliation
A12: RC-009 | B12: FX rate source verification | C12: Daily | D12: Middle Office | E12: FUND 3.9 | F12: FX source log, multi-vendor comparison for material exposures
A13: RC-010 | B13: Regulatory transaction reporting reconciliation (vs SUP 15A) | C13: Daily | D13: Compliance | E13: SUP 15A MAR (UK) | F13: EMIR / MiFIR reporting recon, rejection and resubmission log
A14: RC-011 | B14: Break ageing and escalation review | C14: Weekly | D14: Head of Operations | E14: SYSC 9.1 PRIN 2A | F14: Aged breaks report, escalation evidence, resolution timelines
A15: RC-012 | B15: Quarterly CASS compliance assurance review | C15: Quarterly | D15: CASS Oversight Fn | E15: CASS 6 CASS 7 SUP 3.10 | F15: CASS resolution pack, external auditor CASS report

Sheet Legend & Instructions
A1: WORKBOOK GUIDE
A3: Sheet | B3: Purpose
A4: IBOR - Book of Records | B4: Master investment book of records showing all positions, valuations, and high-level custodian comparison. This is the 'golden source'.
A5: Custodian Reconciliation | B5: Detailed position-by-position reconciliation of IBOR quantities and values against the custodian statement (BNY Mellon). Breaks flagged.
A6: Market Data Reconciliation | B6: Cross-check of closing prices from primary vendor (Bloomberg) against secondary vendor (Refinitiv) and custodian-supplied prices. Includes stale price check.
A7: Corporate Actions | B7: Log of all corporate action events, entitlement calculations, and reconciliation of IBOR-calculated entitlements vs custodian-credited amounts.
A8: Regulatory Reference | B8: Complete list of FCA regulations, retention periods, and their relevance to the reconciliation and record-keeping process.
A9: Recon Controls Framework | B9: Governance controls showing what reconciliation is done, how often, who owns it, and what evidence must be retained for FCA review.
A12: COLOUR KEY
A13: Green highlight | B13: Matched — within tolerance
A14: Red highlight | B14: Break — outside tolerance, investigation required
A15: Yellow highlight | B15: Input cell — user should populate
A16: Amber highlight | B16: Warning — review required
A18: FONT COLOUR KEY
A19: Blue text | B19: Hardcoded input value
A20: Green text | B20: Cross-sheet reference (link to another tab)
A21: Red text | B21: Error or critical break requiring action
